{"quiz": "КОЛИЧЕСТВО УМЫВАЛЬНИКОВ ПЕРЕД ВХОДОМ В СТОЛОВУЮ УСТАНАВЛИВАЕТСЯ ИЗ РАСЧЕТА ОДИН КРАН НА:", "answers": ["20 посадочных мест", "25 посадочных мест", "30 посадочных мест", "50 посадочных мест"], "correct_answers": ["20 посадочных мест"]}
{"quiz": "МАРКИРОВКА РАЗДЕЛОЧНЫХ ДОСОК И НОЖЕЙ «ВО» ОЗНАЧАЕТ:", "answers": ["вареный окунь", "вареные овощи", "варка обязательна", "вымыть осторожно"], "correct_answers": ["вареные овощи"]}
{"quiz": "МИНИМАЛЬНОЕ КОЛИЧЕСТВО МЯСОРУБОК НА ПИЩЕБЛОКЕ:", "answers": ["три", "две", "одна", "четыре"], "correct_answers": ["две"]}
{"quiz": "СКОРОПОРТЯЩИЕСЯ ПРОДУКТЫ (МЯСО, РЫБА) ЗАПАСАЮТ НА ПИЩЕБЛОКЕ НА СРОК НЕ БОЛЕЕ ЧЕМ:", "answers": ["3 суток", "4 суток", "5 суток", "7 суток"], "correct_answers": ["3 суток"]}
{"quiz": "РАЗДЕЛКА ОВОЩЕЙ ДЛЯ ПРИГОТОВЛЕНИЯ САЛАТА ИЗ СЫРЫХ ОВОЩЕЙ ДОПУСКАЕТСЯ НА РАЗДЕЛОЧНЫХ ДОСКАХ С МАРКИРОВКОЙ:", "answers": ["«СО»", "«ВО»", "«КО»", "«МГ»"], "correct_answers": ["«ВО»"]}
{"quiz": "ПОСЛЕ ОБЖАРИВАНИЯ В КИПЯЩЕМ ЖИРЕ В ТЕЧЕНИЕ 10 МИНУТ С ОБЕИХ СТОРОН КОТЛЕТЫ, БИТОЧКИ И ДРУГИЕ ИЗДЕЛИЯ ИЗ РЫНОГО ИЛИ МЯСНОГО ФАРША ДОЛЖНЫ БЫТЬ:", "answers": ["обработаны паром", "обработаны кипятком", "немедленно охлаждены и помещены в холодильник", "выдержаны в духовом шкафу в течение 5-8 мин. при температуре 220-250°С"], "correct_answers": ["выдержаны в духовом шкафу в течение 5-8 мин. при температуре 220-250°С"]}
{"quiz": "* ВИДЫ ТЕПЛОВОЙ ОБРАБОТКИ ПРОДУКТОВ:", "answers": ["варка", "жарение", "запекание", "бланшировка"], "correct_answers": ["варка", "жарение", "запекание", "бланшировка"]}
{"quiz": "* ВИДЫ УБОРКИ НА ПИЩЕБЛОКЕ (В ЗАВИСИМОСТИ ОТ ЧАСТОТЫ):", "answers": ["текущая", "ежедневная", "ежемесячная", "еженедельная"], "correct_answers": ["текущая", "ежедневная", "ежемесячная", "еженедельная"]}
{"quiz": "ОПТИМАЛЬНАЯ ОРИЕНТАЦИЯ ОКОН В ЦЕХЕ ДЛЯ ПРИГОТОВЛЕНИЯ ХОЛОДНЫХ ЗАКУСОК И БЛЮД:", "answers": ["южная", "западная", "северная", "восточная"], "correct_answers": ["северная"]}
{"quiz": "ПО ОКОНЧАНИИ РАБОТЫ КОЛОДА ДЛЯ РУБКИ МЯСА ЗАЧИЩАЕТСЯ И ОБРАБАТЫВАЕТСЯ:", "answers": ["водой", "солью", "моющим раствором", "дезинфицирующим раствором"], "correct_answers": ["солью"]}
{"quiz": "СТОЛОВЫЕ ПРИБОРЫ ПОСЛЕ МЫТЬЯ И ОПОЛАСКИВАНИЯ ДОЛЖНЫ БЫТЬ ПРОКАЛЕНЫ В СУХОЖАРОВЫХ ШКАФАХ В ТЕЧЕНИЕ:", "answers": ["1 часа", "5 минут", "10 минут", "25 минут"], "correct_answers": ["10 минут"]}
{"quiz": "* ПРИ ХРАНЕНИИ ПРОДУКТОВ ПИТАНИЯ НЕОБХОДИМО УЧИТЫВАТЬ:", "answers": ["условия хранения", "срок годности продукта", "правила товарного соседства", "время приготовления продукта"], "correct_answers": ["условия хранения", "срок годности продукта", "правила товарного соседства", "время приготовления продукта"]}
{"quiz": "* НА ПИЩЕБЛОКЕ ЗАПРЕЩАЕТСЯ ОСТАВЛЯТЬ НА СЛЕДУЮЩИЙ ДЕНЬ:", "answers": ["супы", "блинчики с мясом", "макароны отварные", "картофельное пюре"], "correct_answers": ["супы", "блинчики с мясом", "макароны отварные", "картофельное пюре"]}
{"quiz": "* СОТРУДНИКИ ПИЩЕБЛОКА ОБЯЗАНЫ:", "answers": ["покрывать ногти бесцветным лаком", "сообщать администрации о заболевании", "подбирать волосы под косынку или колпак", "снимать спецодежду при посещении туалета"], "correct_answers": ["сообщать администрации о заболевании", "подбирать волосы под косынку или колпак", "снимать спецодежду при посещении туалета"]}
{"quiz": "* МАТЕРИАЛЫ ДЛЯ ИЗГОТОВЛЕНИЯ КУХОННОЙ ПОСУДЫ, ИСПОЛЬЗУЕМОЙ НА ПИЩЕБЛОКЕ:", "answers": ["цинк", "эмаль", "алюминий", "нержавеющая сталь"], "correct_answers": ["алюминий", "нержавеющая сталь"]}
{"quiz": "* ПРИ ОРГАНИЗАЦИИ ПИТАНИЯ В ДЕТСКИХ КОЛЛЕКТИВАХ ЗАПРЕЩАЕТСЯ:", "answers": ["употреблять грибы в пищу", "принимать непотрошеных кур и индеек", "принимать консервы домашнего приготовления", "принимать консервы без термической обработки"], "correct_answers": ["употреблять грибы в пищу", "принимать непотрошеных кур и индеек", "принимать консервы домашнего приготовления", "принимать консервы без термической обработки"]}
{"quiz": "КОЛИЧЕСТВО СЕКЦИЙ МОЕЧНОЙ ВАННЫ, НЕОБХОДИМОЕ ДЛЯ МЫТЬЯ СТОЛОВОЙ ПОСУДЫ:", "answers": ["две", "три", "пять", "четыре"], "correct_answers": ["три"]}
{"quiz": "ГЕНЕРАЛЬНАЯ УБОРКА ПРОИЗВОДСТВЕНЫХ ПОМЕЩЕНИЙ ПИЩЕБЛОКА ДОЛЖНА ПРОВОДИТЬСЯ:", "answers": ["ежедневно", "ежемесячно", "еженедельно", "по мере необходимости"], "correct_answers": ["еженедельно"]}
{"quiz": "КОЛИЧЕСТВО СЕКЦИЙ МОЕЧНОЙ ВАННЫ, НЕОБХОДИМОЕ ДЛЯ МЫТЬЯ КУХОННОЙ ПОСУДЫ:", "answers": ["две", "три", "пять", "четыре"], "correct_answers": ["две"]}
{"quiz": "ЧАСТОТА ГИГИЕНИЧЕСКОЙ ПОДГОТОВКИ И ПЕРЕПОДГОТОВКИ ПЕРСОНАЛА ПИЩЕБЛОКА:", "answers": ["один раз в год", "один раз в три года", "один раз в два года", "по мере необходимости"], "correct_answers": ["один раз в два года"]}
{"quiz": "КОЛИЧЕСТВО СЕКЦИЙ МОЕЧНОЙ ВАННЫ, НЕОБХОДИМОЕ ДЛЯ МЫТЬЯ ЯИЦ:", "answers": ["две", "три", "одна", "четыре"], "correct_answers": ["четыре"]}
{"quiz": "К РАБОТЕ НА ПИЩЕБЛОКЕ НЕ ДОПУСКАЮТСЯ ЛИЦА, СТРАДАЮЩИЕ:", "answers": ["глаукомой", "венерическими заболеваниями", "заболеваниями щитовидной железы", "сердечно-сосудистыми заболеваниями"], "correct_answers": ["венерическими заболеваниями"]}
{"quiz": "ОРГАНИЗАЦИИ ОБЩЕСТВЕННОГО ПИТАНИЯ НЕ РАЗРЕШАЕТСЯ РАЗМЕЩАТЬ В:", "answers": ["жилых зданиях", "общественных зданиях", "пристройках к жилым и общественным зданиям", "подвальных и полуподвальных помещениях жилых и общественных зданий"], "correct_answers": ["подвальных и полуподвальных помещениях жилых и общественных зданий"]}
{"quiz": "ВЫСОТА ОТДЕЛКИ СТЕН КАФЕЛЕМ (МАСЛЯНОЙ КРАСКОЙ) В ПРОИЗВОДСТВЕННЫХ ПОМЕЩЕНИЯХ ПРЕДПРИЯТИЙ ОБЩЕСТВЕННОГО ПИТАНИЯ:", "answers": ["1,0-1,5 м", "1,5-1,8 м", "1,8-2,0 м", "2,0-2,2 м"], "correct_answers": ["1,5-1,8 м"]}
{"quiz": "ТЕМПЕРАТУРА ВОДЫ ДЛЯ ОПОЛАСКИВАНИЯ КУХОННОЙ ИСТОЛОВОЙ ПОСУДЫ:", "answers": ["не менее 45°С", "не менее 50°С", "не менее 60°С", "не менее 65°С"], "correct_answers": ["не менее 65°С"]}
{"quiz": "ТЕМПЕРАТУРА ВОДЫ ДЛЯ ОПОЛАСКИВАНИЯ КУХОННОЙ ИСТОЛОВОЙ ПОСУДЫ:", "answers": ["выжигание", "гравировка", "масляная краска", "химический карандаш"], "correct_answers": ["выжигание"]}
{"quiz": "ВИД ОБРАБОТКИ ПИЩЕВЫХ ПРОДУКТОВ, НЕ ОТНОСЯЩИЙСЯ К ХОЛОДОВОЙ ОБРАБОТКЕ:", "answers": ["сортировка", "вымачивание", "процеживание", "бланширование"], "correct_answers": ["бланширование"]}
{"quiz": "* ВИДЫ ТЕПЛОВОЙ ОБРАБОТКИ ПИЩЕВЫХ ПРОДУКТОВ:", "answers": ["варка", "тушение", "запекание", "мытье горячей водой"], "correct_answers": ["варка", "тушение", "запекание"]}
{"quiz": "МЕСТО ХРАНЕНИЯ САНИТАРНЫХ КНИЖЕК РАБОТНИКОВ ПИЩЕБЛОКА:", "answers": ["дома у работника", "в медицинском учреждении", "у ответственного лица на пищеблоке", "у ответственного лица Роспотребнадзора"], "correct_answers": ["у ответственного лица на пищеблоке"]}
{"quiz": "* СТОЛОВУЮ ПОСУДУ МОЮТ: (если попросят выбрать только 1 ответ, то \"сразу после использования\", если несколько - то еще \"в конце рабочего дня\". Сейчас укажи оба)", "answers": ["в конце рабочего дня", "по мере необходимости", "сразу после использования", "непосредственно перед использованием"], "correct_answers": ["в конце рабочего дня", "сразу после использования"]}
{"quiz": "МАКСИМАЛЬНЫЙ ОБЪЕМ ЗАПОЛНЕНИЯ МУСОРОСБОРНИКОВ И ВЫГРЕБНЫХ ЯМ:", "answers": ["две трети", "половина", "одна треть", "полный объем"], "correct_answers": ["две трети"]}
{"quiz": "ЧАСТОТА ПРОВЕДЕНИЯ «САНИТАРНОГО ДНЯ» НА ПРЕДПРИЯТИЯХ ОБЩЕСТВЕННОГО ПИТАНИЯ:", "answers": ["1 раз в год", "2 раза в год", "два раза в месяц", "один раз в месяц"], "correct_answers": ["один раз в месяц"]}
{"quiz": "НА ПРЕДПРИЯТИЯХ ОБЩЕСТВЕННОГО ПИТАНИЯ ДЛЯ ОКРАСКИ СТЕН ПРОИЗВОДСТВЕННЫХ ПОМЕЩЕНИЙ ПРЕДПОЧТИТЕЛЬНЕЕ ИПОЛЬЗОВАТЬ:", "answers": ["темные тона", "светлые тона", "тон не имеет значения", "тон окраски зависит от предназначения помещения"], "correct_answers": ["светлые тона"]}
{"quiz": "КОЛИЧЕСТВО ТИПОВ ПИЩЕБЛОКОВ ПРЕДПРИЯТИЙ ОБЩЕСТВЕННОГО ПИТАНИЯ:", "answers": ["2", "3", "4", "5"], "correct_answers": ["3"]}
{"quiz": "ОСНОВНЫЕ ТИПЫ ТЕПЛОВОЙ ОБРАБОТКИ ПРОДУКТОВ НА ПИЩЕБЛОКЕ:", "answers": ["варка и тушение", "варка и жарение", "варка и запекание", "жарение и варка на пару"], "correct_answers": ["варка и жарение"]}
{"quiz": "СМЕШИВАНИЕ СВЕЖЕПРИГОТОВЛЕННОЙ ПИЩИ С АНАЛОГИЧНОЙ ПИЩЕЙ, ОСТАВШЕЙСЯ ОТ ПРЕДЫДУЩЕГО ДНЯ НА ПИЩЕБЛОКЕ:", "answers": ["запрещено для напитков", "запрещено для первых блюд", "запрещено для любых блюд", "разрешено только для напитков"], "correct_answers": ["запрещено для любых блюд"]}
{"quiz": "ДЛЯ ПОДДЕРЖАНИЯ ОПТИМАЛЬНОЙ ТЕМПЕРАТУРЫ БЛЮД НА РАЗДАЧЕ ИСПОЛЬЗУЮТ:", "answers": ["мармит", "термостат", "электроплиты", "электрокипятильники"], "correct_answers": ["мармит"]}
{"quiz": "ГОТОВЫЕ ПЕРВЫЕ И ВТОРЫЕ БЛЮДА В ПРОЦЕССЕ РЕАЛИЗАЦИИ МОГУТ НАХОДИТЬСЯ НА МАРМИТЕ НЕ БОЛЕЕ:", "answers": ["1 часа", "2-3 часов", "3-4 часов", "4-5 часов"], "correct_answers": ["2-3 часов"]}
{"quiz": "ЧАСТОТА МЕДИЦИНСКИХ ОСМОТРОВ РАБОТНИКОВ ПИЩЕБЛОКА ДЕРМАТОВЕНЕРОЛОГОМ:", "answers": ["2 раза в год", "1 раз в год", "ежеквартально", "1 раз в два года"], "correct_answers": ["1 раз в год"]}
{"quiz": "СПОСОБ ХРАНЕНИЯ РАЗДЕЛОЧНЫХ ДОСОК НА ПИЩЕБЛОКЕ:", "answers": ["на рабочих столах", "в подвешенном виде", "сложенными в стопки в специальных шкафах", "установленными на ребро в специальных кассетах"], "correct_answers": ["установленными на ребро в специальных кассетах"]}
{"quiz": "ОТБОР ПРОБ ГОТОВЫХ БЛЮД НА ПРЕДПИЯТИЯХ ОБЩЕСТВЕННОГО ПИТАНИЯ ДЛЯ ЛАБОРАТОРНОГО ИССЛЕДОВАНИЯ ПРОИЗВОДЯТ:", "answers": ["только из котла", "только с раздачи", "с подноса посетителя", "и с раздачи, и из котла"], "correct_answers": ["только из котла"]}
{"quiz": "МЯСНОЙ ФАРШ НА ПИЩЕБЛОКЕ ХРАНЯТ НЕ БОЛЕЕ:", "answers": ["3 часов", "6 часов", "9 часов", "12 часов"], "correct_answers": ["12 часов"]}
{"quiz": "ЛИЦА С ГНОЙНИЧКОВЫМИ ЗАБОЛЕВАНИЯМИ КОЖИ НЕ ДОПУСКАЮТСЯ К РАБОТЕ:", "answers": ["только в горячих кондитерских цехах", "только в холодных кондитерских цехах", "в холодных и горячих кондитерских цехах"], "correct_answers": ["в холодных и горячих кондитерских цехах"]}
{"quiz": "ПОРЦИОНИРОВАНИЕ ХОЛОДНЫХ ЗАКУСОК НА ПИЩЕБЛОКЕ ДОЛЖНО ПРОВОДИТЬСЯ В ПОМЕЩЕНИЯХ С ТЕМПЕРАТУРОЙ ВОЗДУХА НЕ ВЫШЕ:", "answers": ["+5°С", "+12°С", "+16°С", "+20°С"], "correct_answers": ["+16°С"]}
{"quiz": "НАИБОЛЕЕ НАДЕЖНЫЙ С ЭПИДЕМИОЛОГИЧЕСКОЙ ТОЧКИ ЗРЕНИЯ СПОСОБ ТЕПЛОВОЙ ОБРАБОТКИ ПРОДУКТА:", "answers": ["варка", "жарение", "тушение", "бланширование"], "correct_answers": ["варка"]}
{"quiz": "МАРКИРОВКА РАЗДЕЛОЧНОЙ ДОСКИ «СО» ОЗНАЧАЕТ:", "answers": ["сырые овощи", "соленые овощи", "сильная обжарка", "средняя обжарка"], "correct_answers": ["сырые овощи"]}
{"quiz": "БЛЮДА, ДЕГУСТИРУЕМЫЕ ПРИ БРАКЕРАЖЕ В ПОСЛЕДНЮЮ ОЧЕРЕДЬ:", "answers": ["первые", "вторые", "сладкие", "холодные закуски"], "correct_answers": ["сладкие"]}
{"quiz": "МЕТАЛЛИЧЕСКИЙ ИНВЕНТАРЬ НА ПИЩЕБЛОКЕ ПОСЛЕ МЫТЬЯ ПОДВЕРГАЕТСЯ:", "answers": ["прокаливанию", "обработке паром", "замачиванию в дезрастворе", "ошпариванию кипящей водой"], "correct_answers": ["прокаливанию"]}
{"quiz": "ДОСТАВКА МОЛОКА НА ПИЩЕБЛОК ОСУЩЕСТВЛЯЕТСЯ:", "answers": ["ежедневно", "еженедельно", "один раз в три дня", "по мере необходимости"], "correct_answers": ["ежедневно"]}
{"quiz": "* ПИЩЕВЫЕ ПРОДУКТЫ, ИСПОЛЬЗОВАНИЕ КОТОРЫХ БЕЗ ТЕРМИЧЕСКОЙ ОБРАБОТКИ, ЗАПРЕЩЕНО В ДЕТСКИХ УЧРЕЖДЕНИЯХ:", "answers": ["кефир", "творог", "сметана", "сливочное масло"], "correct_answers": ["творог", "сметана"]}
{"quiz": "ГОТОВЫЕ ПЕРВЫЕ И ВТОРЫЕ БЛЮДА ДО МОМЕНТА ВЫДАЧИ БОЛЬНЫМ ИЛИ ДЕТЯМ ДОЛЖНЫ НАХОДИТЬСЯ НА ГОРЯЧЕЙ ПЛИТЕ НЕ БОЛЕЕ:", "answers": ["4-5 часов", "3-4 часов", "2-3 часов", "1-2 часов"], "correct_answers": ["2-3 часов"]}
{"quiz": "МЕТОД, ПРИ ПОМОЩИ КОТОРОГО ОЦЕНИВАЕТСЯ КАЧЕСТВО ГОТОВЫХ БЛЮД В ПРОЦЕССЕ БРАКЕРАЖА:", "answers": ["химический", "биологический", "органолептический", "бактериоскопический"], "correct_answers": ["органолептический"]}
{"quiz": "* В ПРОЦЕССЕ БРАКЕРАЖА ОПРЕДЕЛЯЕТСЯ:", "answers": ["химический состав пищи", "доброкачественность пищи", "кулинарная готовность пищи", "бактериологическая безопасность пищи"], "correct_answers": ["доброкачественность пищи", "кулинарная готовность пищи"]}
{"quiz": "СРОК ХРАНЕНИЯ ПРОБЫ ПИЩИ В ХОЛОДИЛЬНИКЕ ПОСЛЕ ПРОВЕДЕНИЯ БРАКЕРАЖА:", "answers": ["6 часов", "24 часа", "12 часов", "48 часов"], "correct_answers": ["24 часа"]}
{"quiz": "СПОСОБ МЫТЬЯ ГИБОВ И ЗЕЛЕНИ НА ПИЩЕБЛОКЕ:", "answers": ["под струей проточной воды", "методом однократного погружения в емкость с водой", "методом многократного погружения в емкость с большим количеством воды", "методом погружения в емкость с водой с добавлением поваренной соли"], "correct_answers": ["методом многократного погружения в емкость с большим количеством воды"]}
{"quiz": "ОЧИЩЕННЫЙ КАРТОФЕЛЬ КЛУБНЯМИ МОЖНО ХРАНИТЬ В ХОЛОДНОЙ ВОДЕ НЕ БОЛЕЕ:", "answers": ["5-6 часов", "4-5 часов", "3-4 часов", "2-3 часов"], "correct_answers": ["2-3 часов"]}
{"quiz": "РАЗМОРАЖИВАНИЕ РЫБЫ ОСУЩЕСТВЛЯЕТСЯ:", "answers": ["в холодной воде", "в холодной воде с добавлением соли", "в холодильных камерах при температуре от 0 до +6°С", "на столе рыбного цеха при температуре воздуха +18°С"], "correct_answers": ["в холодной воде с добавлением соли"]}
{"quiz": "* ЯДОВИТЫЕ ГРИБЫ", "answers": ["сморчки", "строчки", "грузди", "сатанинский гриб", "мухомор"], "correct_answers": ["строчки", "сатанинский гриб", "мухомор"]}
{"quiz": "* ЯДОВИТЫЕ ВЕЩЕСТВА СТРОЧКОВ", "answers": ["мускарин", "фаллоидин", "гельвеловая кислота", "гиромитрин"], "correct_answers": ["гельвеловая кислота", "гиромитрин"]}
{"quiz": "* ЯДЫ БЛЕДНОЙ ПОГАНКИ", "answers": ["фаллоидин", "α -аманитин", "β-аманитин", "гиромитрин", "γ -аманитин", "гельвеловая кислота"], "correct_answers": ["фаллоидин", "α -аманитин", "β-аманитин", "γ -аманитин"]}
{"quiz": "* ЯДОВИТЫЕ ВЕЩЕСТВА МУХОМОРОВ", "answers": ["гиромитрин", "гельвеловая кислота", "мускарин", "мускаридин"], "correct_answers": ["мускарин", "мускаридин"]}
{"quiz": "ЯДОВИТОЕ НАЧАЛО СМОРЧКОВ", "answers": ["мускарин", "фаллоидин", "гельвеловая кислота", "гиромитрин"], "correct_answers": ["гельвеловая кислота"]}
{"quiz": "СПОСОБЫ УДАЛЕНИЯ ГЕЛЬВЕЛОВОЙ КИСЛОТЫ ИЗ СМОРЧКОВ", "answers": ["тщательное мытье", "длительное вымачивание в воде с добавлением соли", "однократное отваривание в воде с последующим удалением отвара", "двукратное отваривание в воде с последующим удалением отвара"], "correct_answers": ["двукратное отваривание в воде с последующим удалением отвара"]}
{"quiz": "* ПРОФИЛАКТИКА ОТРАВЛЕНИЙ ЯДОВИТЫМИ ГРИБАМИ", "answers": ["санитарно-просветельная работа", "соблюдение правил сбора и продажи грибов", "правильная кулинарная обработка", "знание правил оказания первой помощи при отравлениях грибами"], "correct_answers": ["санитарно-просветельная работа", "соблюдение правил сбора и продажи грибов"]}
{"quiz": "* СОРНЯКОВЫЕ ТОКСИКОЗЫ", "answers": ["отравление плевелом опьяняющим", "отравление «пьяным хлебом»", "триходесмотоксикоз", "гелиотропный токсикоз", "афлатоксикоз"], "correct_answers": ["отравление плевелом опьяняющим", "триходесмотоксикоз", "гелиотропный токсикоз"]}
{"quiz": "КЛИНИЧЕСКАЯ КАРТИНА ТРИХОДЕСМОТОКСИКОЗА", "answers": ["менингоэнцефалит", "токсический гепатит", "почечная недостаточность", "дыхательная недостаточность"], "correct_answers": ["менингоэнцефалит"]}
{"quiz": "КЛИНИЧЕСКАЯ КАРТИНА ГЕЛИОТРОПНОГО ТОКСИКОЗА", "answers": ["менингоэнцефалит", "токсический гепатит", "почечная недостаточность", "дыхательная недостаточность"], "correct_answers": ["токсический гепатит"]}
{"quiz": "ЭТИОЛОГИЧЕСКИЙ ФАКТОР ПИЩЕВОГО ОТРАВЛЕНИЯ ПЛЕВЕЛОМ ОПЬЯНЯЮЩИМ", "answers": ["грибы рода Fusarium graminearum", "грибы рода Fusarium sporotrichioides", "грибы рода Stromatinia temulenta", "грибы рода Aspergillus flavus"], "correct_answers": ["грибы рода Stromatinia temulenta"]}
{"quiz": "* ЯДОВИТЫЕ РАСТЕНИЯ", "answers": ["красавка обыкновенная", "ландыш майский", "плевел опьяняющий", "триходесма седая", "гелиотроп опушенноплодный", "белена черная"], "correct_answers": ["красавка обыкновенная", "ландыш майский", "плевел опьяняющий", "триходесма седая", "гелиотроп опушенноплодный", "белена черная"]}
{"quiz": "* ПИЩЕВЫЕ ОТРАВЛЕНИЯ ПРОДУКТАМИ РАСТИТЕЛЬНОГО ПРОИСХОЖДЕНИЯ, ЯДОВИТЫМИ ПРИ ОПРЕДЕЛЕННЫХ УСЛОВИЯХ", "answers": ["отравления ядрами косточковых плодов", "отравления спорыньей", "отравления сырой фасолью", "гелиотропный токсикоз", "отравления буковыми орехами", "отравление плевелом опьяняющим", "отравления строчками"], "correct_answers": ["отравления ядрами косточковых плодов", "отравления сырой фасолью", "отравления буковыми орехами"]}
{"quiz": "* ПИЩЕВЫЕ ОТРАВЛЕНИЯ ПРОДУКТАМИ РАСТИТЕЛЬНОГО ПРОИСХОЖДЕНИЯ, ЯДОВИТЫМИ ПО СВОЕЙ ПРИРОДЕ", "answers": ["пищевое отравление ядрами косточковых плодов", "пищевое отравление спорыньей", "триходесмотоксикоз", "пищевое отравление беленой", "пищевое отравление буковыми орехами", "пищевое отравление плевелом опьяняющим", "пищевое отравление строчками"], "correct_answers": ["триходесмотоксикоз", "пищевое отравление беленой", "пищевое отравление плевелом опьяняющим", "пищевое отравление строчками"]}
{"quiz": "* ПРОДУКТЫ ЖИВОТНОГО ПРОИСХОЖДЕНИЯ, ЯДОВИТЫЕ ПРИ ОПРЕДЕЛЕННЫХ УСЛОВИЯХ", "answers": ["печень, икра и молоки некоторых рыб в период нереста", "мед пчелиный при сборе пчелами нектара с ядовитых растений", "моллюски в определенные периоды года", "железы внутренней секреции крупного убойного скота", "печень икра, молоки ядовитых рыб"], "correct_answers": ["печень, икра и молоки некоторых рыб в период нереста", "мед пчелиный при сборе пчелами нектара с ядовитых растений", "моллюски в определенные периоды года"]}
{"quiz": "ДЕЙСТВУЮЩЕЕ ВЕЩЕСТВО ПРИ ПИЩЕВОМ ОТРАВЛЕНИИ ПРОРОСШИМ ПОЗЕЛЕНЕВШИМ КАРТОФЕЛЕМ", "answers": ["гиромитрин", "амигдалин", "соланин", "фазин", "фагин"], "correct_answers": ["соланин"]}
{"quiz": "ДЕЙСТВУЮЩЕЕ ВЕЩЕСТВО ПРИ ПИЩЕВОМ ОТРАВЛЕНИИ ЯДРАМИ КОСТОЧКОВЫХ ПЛОДОВ", "answers": ["гиромитрин", "амигдалин", "соланин", "фазин", "фагин"], "correct_answers": ["амигдалин"]}
{"quiz": "ДЕЙСТВУЮЩЕЕ ВЕЩЕСТВО ПРИ ПИЩЕВОМ ОТРАВЛЕНИИ БОБАМИ СЫРОЙ ФАСОЛИ", "answers": ["гиромитрин", "амигдалин", "соланин", "фазин", "фагин"], "correct_answers": ["фазин"]}
{"quiz": "ДЕЙСТВУЮЩЕЕ ВЕЩЕСТВО ПРИ ПИЩЕВОМ ОТРАВЛЕНИИ СЫРЫМИ БУКОВЫМИ ОРЕХАМИ", "answers": ["гиромитрин", "амигдалин", "соланин", "фазин", "фагин"], "correct_answers": ["фагин"]}
{"quiz": "* УСЛОВНО-СЬЕДОБНЫЕ ГРИБЫ", "answers": ["сморчки", "строчки", "грузди", "сатанинский гриб", "волнушки"], "correct_answers": ["сморчки", "грузди", "волнушки"]}
{"quiz": "* ПРОФИЛАКТИКА ПИЩЕВЫХ ОТРАВЛЕНИЙ УСЛОВНО-СЪЕДОБНЫМИ ГРИБАМИ", "answers": ["санитарно-просветительная работа", "соблюдение правил сбора и продажи грибов", "правильная кулинарная обработка", "знание правил оказания первой помощи при отравлениях грибами"], "correct_answers": ["санитарно-просветительная работа", "соблюдение правил сбора и продажи грибов", "правильная кулинарная обработка", "знание правил оказания первой помощи при отравлениях грибами"]}
{"quiz": "* ПИЩЕВЫЕ ОТРАВЛЕНИЯ ПРИМЕСЯМИ ХИМИЧЕСКИХ ВЕЩЕСТВ", "answers": ["пестицидами", "соланином", "пищевыми добавками", "фазином", "солями тяжелых металлов", "нитратами"], "correct_answers": ["пестицидами", "пищевыми добавками", "солями тяжелых металлов", "нитратами"]}
{"quiz": "* ИСТОЧНИКИ ПОСТУПЛЕНИЯ НИТРАТОВ В ОРГАНИЗМ", "answers": ["корнеплоды", "молочные продукты", "колбасные изделия", "зерновые продукты", "вода"], "correct_answers": ["корнеплоды", "колбасные изделия", "вода"]}
{"quiz": "* ЧАСТИ РАСТЕНИЙ, КУМУЛИРУЮЩИЕ НИТРАТЫ", "answers": ["кожура", "сердцевина", "часть плода, прилегающая к стеблю", "часть плода, находящая на другой стороне от стебля", "толстые жилки"], "correct_answers": ["кожура", "сердцевина", "часть плода, прилегающая к стеблю", "толстые жилки"]}
{"quiz": "ВРЕМЯ СУТОК, ХАРАКТЕРИЗУЮЩЕЕСЯ МИНИМАЛЬНЫМ СОДЕРЖАНИЕМ НИТРАТОВ В ОВОЩАХ И ФРУКТАХ", "answers": ["утро", "полдень", "послеобеденное время", "вечер"], "correct_answers": ["вечер"]}
{"quiz": "ЗАБОЛЕВАНИЕ, СВЯЗАННОЕ С ИЗБЫТОЧНЫМ ПОСТУПЛЕНИЕМ В ОРГАНИЗМ НИТРАТОВ", "answers": ["железодефицитная анемия", "нитрато-нитритная метгемоглобинемия", "пароксизмально-токсическая миоглобинурия", "алиментарно-токсическая алейкия"], "correct_answers": ["нитрато-нитритная метгемоглобинемия"]}
{"quiz": "* ПРИЧИНЫ ПОВЫШЕННОЙ ВОСПРИИМЧИВОСТИ ДЕТЕЙ ГРУДНОГО ВОЗРАСТА К ВОЗДЕЙСТВИЮ НИТРАТОВ", "answers": ["фетальный гемоглобин", "нулевая кислотность желудочного сока", "высокая кислотность желудочного сока", "отсутствие метгемоглобинредуктазы", "большое количество метгемоглобинредуктазы"], "correct_answers": ["фетальный гемоглобин", "нулевая кислотность желудочного сока", "отсутствие метгемоглобинредуктазы"]}
{"quiz": "МИТИЛИЗМ", "answers": ["отравление ртутью", "отравление мидиями", "отравление свинцом", "отравление рыбой фугу"], "correct_answers": ["отравление мидиями"]}
{"quiz": "САТУРНИЗМ", "answers": ["отравление ртутью", "отравление мидиями", "отравление свинцом", "отравление рыбой фугу"], "correct_answers": ["отравление свинцом"]}
{"quiz": "* КЛИНИЧЕСКИЕ СИМПТОМЫ ОТРАВЛЕНИЯ СВИНЦОМ", "answers": ["серо-голубая кайма на деснах", "коричневая кайма на деснах", "почечная колика", "коликообразные боли в животе", "серая окраска кожи", "цианоз", "запор", "диарея"], "correct_answers": ["серо-голубая кайма на деснах", "коликообразные боли в животе", "серая окраска кожи", "диарея"]}
{"quiz": "* НАИБОЛЕЕ ОПАСНЫЕ СВОЙСТВА ПЕСТИЦИДОВ", "answers": ["высокая стойкость во внешней среде", "высокая токсичность", "высокая растворимость", "способность выделяться с молоком", "выраженные кумулятивные свойства"], "correct_answers": ["высокая стойкость во внешней среде", "высокая токсичность", "способность выделяться с молоком", "выраженные кумулятивные свойства"]}
{"quiz": "СВОЙСТВА ХЛОРОРГАНИЧЕСКИХ ПЕСТИЦИДОВ", "answers": ["высокая токсичность и высокая персистентность", "высокая токсичностью и низкая персистентность", "низкая токсичность и высокая персистентность", "низкая токсичность и низкая персистентность"], "correct_answers": ["высокая токсичность и высокая персистентность"]}
{"quiz": "* СОСТАВНЫЕ ЧАСТИ ПИЩЕВЫХ ПРОДУКТОВ", "answers": ["питательные вещества", "антипитательные вещества", "чужеродные вещества", "эссенциальные вещества"], "correct_answers": ["питательные вещества", "антипитательные вещества", "чужеродные вещества"]}
{"quiz": "* ВИДЫ ПИТАТЕЛЬНЫХ ВЕЩЕСТВ", "answers": ["вкусовые", "антивкусовые", "пищевые", "антипищевые"], "correct_answers": ["вкусовые", "пищевые"]}
{"quiz": "* АНТИПИТАТЕЛЬНЫЕ ВЕЩЕСТВА", "answers": ["органические кислоты", "антиаминокислоты", "кетоны", "антивитамины", "дубильные вещества", "антиминеральные вещества"], "correct_answers": ["антиаминокислоты", "антивитамины", "антиминеральные вещества"]}
{"quiz": "* ВКУСОВЫЕ ВЕЩЕСТВА", "answers": ["органические кислоты", "антиаминокислоты", "кетоны", "антивитамины", "дубильные вещества", "антиминеральные вещества"], "correct_answers": ["органические кислоты", "кетоны", "дубильные вещества"]}
{"quiz": "* ПИЩЕВЫЕ ВЕЩЕСТВА", "answers": ["белки", "органические кислоты", "кетоны", "углеводы", "витамины", "жиры", "минеральные соли"], "correct_answers": ["белки", "углеводы", "витамины", "жиры", "минеральные соли"]}
{"quiz": "* ЧУЖЕРОДНЫЕ ВЕЩЕСТВА", "answers": ["нитрозамины", "радиоактивные вещества", "кетоны", "соли тяжелых металлов", "дубильные вещества"], "correct_answers": ["нитрозамины", "радиоактивные вещества", "соли тяжелых металлов"]}
{"quiz": "* ВИДЫ ПИТАНИЯ", "answers": ["рациональное", "профилактическое", "диетическое", "здоровое", "лечебное"], "correct_answers": ["рациональное", "профилактическое", "диетическое", "здоровое", "лечебное"]}
{"quiz": "* ВИДЫ ПИТАНИЯ БОЛЬНОГО ЧЕЛОВЕКА", "answers": ["рациональное", "профилактическое", "диетическое", "здоровое", "лечебное"], "correct_answers": ["диетическое", "лечебное"]}
{"quiz": "КОЛИЧЕСТВЕННАЯ СТОРОНА ПИТАНИЯ РЕГЛАМЕНТИРУЕТ", "answers": ["количество потребляемого белка", "количество потребляемых углеводов", "количество потребляемых жиров", "покрытие энергозатрат калорийностью рациона"], "correct_answers": ["покрытие энергозатрат калорийностью рациона"]}
{"quiz": "* ОСНОВНЫЕ ПРИНЦИПЫ РАЦИОНАЛЬНОГО ПИТАНИЯ", "answers": ["рациональность", "умеренность", "сбалансированность", "ритмичность", "адекватность", "расширенность"], "correct_answers": ["умеренность", "сбалансированность", "ритмичность", "расширенность"]}
{"quiz": "* ПРИНЦИП РИТМИЧНОСТИ ВКЛЮЧАЕТ", "answers": ["распределение суточной калорийности между отдельными приемами пищи", "кратность приемов пищи", "интервалы между приемами пищи", "интервал между пробуждением и первым приемом пищи", "интервал между последним приемом пищи и отходом ко сну"], "correct_answers": ["распределение суточной калорийности между отдельными приемами пищи", "кратность приемов пищи", "интервалы между приемами пищи", "интервал между последним приемом пищи и отходом ко сну"]}
{"quiz": "ПРИНЦИП УМЕРЕННОСТИ ОПРЕДЕЛЯЕТ", "answers": ["умеренное потребление белков", "умеренное потребление жиров", "умеренное потребление углеводов", "баланс между поступлением энергии и ее расходом"], "correct_answers": ["баланс между поступлением энергии и ее расходом"]}
{"quiz": "* ОПТИМАЛЬНОЕ РАСПРЕДЕЛЕНИЕ СУТОЧНОЙ КАЛОРИЙНОСТИ МЕЖДУ ОТДЕЛЬНЫМИ ПРИЕМАМИ ПИЩИ ПРИ 3-Х КРАТНОМ ПИТАНИИ", "answers": ["завтрак - 20%", "завтрак - 30 %", "обед - 40%", "обед - 50%", "ужин - 20%", "ужин - 15%"], "correct_answers": ["завтрак - 30 %", "обед - 50%", "ужин - 20%"]}
{"quiz": "ФИЗИОЛОГИЧЕСКАЯ ПОТРЕБНОСТЬ В БЕЛКЕ ДЛЯ ВЗРОСЛОГО НАСЕЛЕНИЯ СОСТАВЛЯЕТ (% КАЛОРИЙНОСТИ СУТОЧНОГО РАЦИОНА) СОГЛАСНО МЕТОДИЧЕСКИМ РЕКОМЕНДАЦИЯМ (МР 2.3.1.0253—21)", "answers": ["10-12%", "12-14%", "14-16%", "16-18%", "18-20%"], "correct_answers": ["12-14%"]}
{"quiz": "ДОЛЯ УГЛЕВОДОВ В ПИТАНИИ ВЗРОСЛОГО НАСЕЛЕНИЯ СОСТАВЛЯЕТ (% КАЛОРИЙНОСТИ СУТОЧНОГО РАЦИОНА) СОГЛАСНО МЕТОДИЧЕСКИМ РЕКОМЕНДАЦИЯМ (МР 2.3.1.0253—21)", "answers": ["40-45%", "46-50%", "50-55%", "56-58%"], "correct_answers": ["56-58%"]}
{"quiz": "УДЕЛЬНЫЙ ВЕС ЖИРОВ В ПИТАНИИ ВЗРОСЛОГО НАСЕЛЕНИЯ СОСТАВЛЯЕТ (% КАЛОРИЙНОСТИ СУТОЧНОГО РАЦИОНА) СОГЛАСНО МЕТОДИЧЕСКИМ РЕКОМЕНДАЦИЯМ (МР 2.3.1.0253—21)", "answers": ["20%", "25%", "30%", "40%"], "correct_answers": ["30%"]}
{"quiz": "УДЕЛЬНЫЙ ВЕС НАСЫЩЕННЫХ ЖИРНЫХ КИСЛОТ В ПИТАНИИ ВЗРОСЛОГО НАСЕЛЕНИЯ СОСТАВЛЯЕТ (% КАЛОРИЙНОСТИ СУТОЧНОГО РАЦИОНА, НЕ БОЛЕЕ) СОГЛАСНО МЕТОДИЧЕСКИМ РЕКОМЕНДАЦИЯМ (МР 2.3.1.0253—21)", "answers": ["10%", "15%", "20%", "25%"], "correct_answers": ["10%"]}
{"quiz": "СУТОЧНАЯ ПОТРЕБНОСТЬ В ВИТАМИНЕ С ДЛЯ ВЗРОСЛЫХ (МГ/СУТКИ) СОГЛАСНО МЕТОДИЧЕСКИМ РЕКОМЕНДАЦИЯМ (МР 2.3.1.0253—21)", "answers": ["70", "80", "90", "100"], "correct_answers": ["100"]}
{"quiz": "ФИЗИОЛОГИЧЕСКАЯ ПОТРЕБНОСТЬ В ПИЩЕВЫХ ВОЛОКНАХ ДЛЯ ВЗРОСЛОГО НАСЕЛЕНИЯ (Г/СУТКИ) СОГЛАСНО МЕТОДИЧЕСКИМ РЕКОМЕНДАЦИЯМ (МР 2.3.1.0253—21)", "answers": ["15-20", "20-25", "25-30", "30-35"], "correct_answers": ["20-25"]}
{"quiz": "ФИЗИОЛОГИЧЕСКАЯ ПОТРЕБНОСТЬ В ЙОДЕ ДЛЯ ВЗРОСЛЫХ (МКГ/СУТКИ) СОГЛАСНО МЕТОДИЧЕСКИМ РЕКОМЕНДАЦИЯМ (МР 2.3.1.0253—21)", "answers": ["100", "150", "1000", "1500"], "correct_answers": ["150"]}
{"quiz": "АДЕКВАТНЫЙ УРОВЕНЬ ПОТРЕБЛЕНИЯ ФТОРА ДЛЯ ВЗРОСЛЫХ (МГ/СУТКИ) СОГЛАСНО МЕТОДИЧЕСКИМ РЕКОМЕНДАЦИЯМ (МР 2.3.1.0253—21)", "answers": ["1", "2", "3", "4"], "correct_answers": ["4"]}
{"quiz": "КОЛИЧЕСТВО ХОЛЕСТЕРИНА, ПОСТУПАЮЩЕГО С ПИЩЕЙ В СУТКИ ДЛЯ ВЗРОСЛЫХ НЕ ДОЛЖНО ПРЕВЫШАТЬ (МГ) СОГЛАСНО МЕТОДИЧЕСКИМ РЕКОМЕНДАЦИЯМ (МР 2.3.1.0253—21)", "answers": ["100", "200", "300", "400"], "correct_answers": ["300"]}
{"quiz": "ПИЩЕВОЙ АНАБОЛИЗМ", "answers": ["процесс синтеза из более простых веществ более сложных, сопровождающийся затратами энергии", "процесс расщепления более сложных веществ до более простых, сопровождающийся выделением энергии", "процесс синтеза из более простых веществ более сложных, сопровождающийся выделением энергии", "процесс расщепления более сложных веществ до более простых, сопровождающийся затратами энергии"], "correct_answers": ["процесс синтеза из более простых веществ более сложных, сопровождающийся затратами энергии"]}
{"quiz": "ПИЩЕВОЙ КАТАБОЛИЗМ", "answers": ["процесс синтеза из более простых веществ более сложных, сопровождающийся затратами энергии", "процесс расщепления более сложных веществ до более простых, сопровождающийся выделением энергии", "процесс синтеза из более простых веществ более сложных, сопровождающийся выделением энергии", "процесс расщепления более сложных веществ до более простых, сопровождающийся затратами энергии"], "correct_answers": ["процесс расщепления более сложных веществ до более простых, сопровождающийся выделением энергии"]}
{"quiz": "* ВИДЫ СУТОЧНЫХ ЭНЕРГОЗАТРАТ", "answers": ["основной обмен", "затраты энергии на умственную деятельность", "специфическое динамическое действие пищи", "затраты энергии на физическую деятельность", "пищевой термогенез"], "correct_answers": ["основной обмен", "затраты энергии на умственную деятельность", "специфическое динамическое действие пищи", "затраты энергии на физическую деятельность", "пищевой термогенез"]}
{"quiz": "* РЕГУЛИРУЕМЫЕ ЭНЕРГОЗАТРАТЫ", "answers": ["основной обмен", "умственная работа", "физическая работа", "пищевой термогенез"], "correct_answers": ["умственная работа", "физическая работа"]}
{"quiz": "* НЕРЕГУЛИРУЕМЫЕ ЭНЕРГОЗАТРАТЫ", "answers": ["основной обмен", "умственная работа", "физическая работа", "пищевой термогенез"], "correct_answers": ["основной обмен", "пищевой термогенез"]}
{"quiz": "* УСЛОВИЯ ИЗМЕРЕНИЯ ОСНОВНОГО ОБМЕНА", "answers": ["утром, натощак", "лёжа, в состоянии покоя после сна", "после активной физической нагрузки", "температурный комфорт", "вечером, после приема пищи"], "correct_answers": ["утром, натощак", "лёжа, в состоянии покоя после сна", "температурный комфорт"]}
{"quiz": "* ФАКТОРЫ, ОПРЕДЕЛЯЮЩИЕ ВЕЛИЧИНУ ОСНОВНОГО ОБМЕНА", "answers": ["масса тела", "пол", "возраст", "вид трудовой деятельности", "состояние эндокринной системы", "эмоциональный статус", "вид умственной деятельности"], "correct_answers": ["масса тела", "пол", "возраст", "состояние эндокринной системы", "эмоциональный статус"]}
{"quiz": "* ПРОЦЕССЫ ПИЩЕВОГО ТЕРМОГЕНЕЗА, ТРЕБУЮЩИЕ ЭНЕРГОЗАТРАТ", "answers": ["пережёвывание пищи", "формирование пищевого комка", "согревание пищи", "секреторная деятельность", "переваривание пищи"], "correct_answers": ["пережёвывание пищи", "формирование пищевого комка", "согревание пищи", "секреторная деятельность", "переваривание пищи"]}
{"quiz": "ПРОЦЕНТНАЯ ДОЛЯ СПЕЦИФИЧЕСКОГО ДИНАМИЧЕСКОГО ДЕЙСТВИЯ ПИЩИ ОТ ВЕЛИЧИНЫ ОСНОВНОГО ОБМЕНА ПРИ СМЕШАННОМ ПИТАНИИ", "answers": ["5 - 10%", "10 % - 15%", "20% - 25%", "40-50%", "50%"], "correct_answers": ["10 % - 15%"]}
{"quiz": "НАИБОЛЬШИМ СПЕЦИФИЧЕСКИМ ДИНАМИЧЕСКИМ ДЕЙСТВИЕМ (СДД) ОБЛАДАЮТ", "answers": ["минеральные соли", "витамины", "углеводы", "белки", "жиры"], "correct_answers": ["белки"]}
{"quiz": "НАИМЕНЬШИМ СПЕЦИФИЧЕСКИМ ДИНАМИЧЕСКИМ ДЕЙСТВИЕМ (СДД) ОБЛАДАЮТ", "answers": ["минеральные соли", "витамины", "углеводы", "белки", "жиры"], "correct_answers": ["углеводы"]}
{"quiz": "КОЛИЧЕСТВО ГРУПП ФИЗИЧЕСКОЙ АКТИВНОСТИ ДЛЯ ЖЕНЩИН", "answers": ["4", "2", "5", "3", "6"], "correct_answers": ["4"]}
{"quiz": "КОЛИЧЕСТВО ГРУПП ФИЗИЧЕСКОЙ АКТИВНОСТИ ДЛЯ МУЖЧИН", "answers": ["4", "5", "3", "6", "2"], "correct_answers": ["4"]}
{"quiz": "* ВОЗРАСТНЫЕ КАТЕГОРИИ ГРУПП ФИЗИЧЕСКОЙ АКТИВНОСТИ", "answers": ["18-29", "30-39", "30-44", "40-59", "45-64"], "correct_answers": ["18-29", "30-44", "45-64"]}
{"quiz": "СРЕДНЯЯ МАССА ТЕЛА МУЖЧИН", "answers": ["60 кг", "65 кг", "70 кг", "75 кг"], "correct_answers": ["70 кг"]}
{"quiz": "СРЕДНЯЯ МАССА ТЕЛА ЖЕНЩИН", "answers": ["60 кг", "65 кг", "70 кг", "75 кг"], "correct_answers": ["60 кг"]}
{"quiz": "ГРУППА ФИЗИЧЕСКОЙ АКТИВНОСТИ С КФА = 1,4", "answers": ["IV", "V", "I", "III", "II"], "correct_answers": ["I"]}
{"quiz": "ГРУППА ФИЗИЧЕСКОЙ АКТИВНОСТИ С КФА = 1,6", "answers": ["I", "II", "III", "IV", "V"], "correct_answers": ["II"]}
{"quiz": "ГРУППА ФИЗИЧЕСКОЙ АКТИВНОСТИ С КФА = 1,9", "answers": ["I", "II", "III", "IV", "V"], "correct_answers": ["III"]}
{"quiz": "ГРУППА ФИЗИЧЕСКОЙ АКТИВНОСТИ С КФА = 1,9", "answers": ["I", "II", "III", "IV", "V"], "correct_answers": ["IV"]}
{"quiz": "ГРУППА ФИЗИЧЕСКОЙ АКТИВНОСТИ ВРАЧА – ХИРУРГА", "answers": ["I группа", "II группа", "III группа", "IV группа", "V группа"], "correct_answers": ["II группа"]}
{"quiz": "ГРУППА ФИЗИЧЕСКОЙ АКТИВНОСТИ СТУДЕНТА", "answers": ["I группа", "II группа", "III группа", "IV группа", "V группа"], "correct_answers": ["I группа"]}
{"quiz": "ГРУППА ФИЗИЧЕСКОЙ АКТИВНОСТИ СТРОИТЕЛЬНОГО РАБОЧЕГО", "answers": ["I группа", "II группа", "III группа", "IV группа", "V группа"], "correct_answers": ["IV группа"]}
{"quiz": "ГРУППА ФИЗИЧЕСКОЙ АКТИВНОСТИ МЕДСЕСТРЫ", "answers": ["I группа", "II группа", "III группа", "IV группа", "V группа"], "correct_answers": ["II группа"]}
{"quiz": "ГРУППА ФИЗИЧЕСКОЙ АКТИВНОСТИ УЧАСТКОВОГО ВРАЧА", "answers": ["I группа", "II группа", "III группа", "IV группа", "V группа"], "correct_answers": ["II группа"]}
{"quiz": "ГРУППА ФИЗИЧЕСКОЙ АКТИВНОСТИ СЛЕСАРЯ", "answers": ["I группа", "II группа", "III группа", "IV группа", "V группа"], "correct_answers": ["III группа"]}
{"quiz": "* МЕТОДЫ ИЗМЕРЕНИЯ СУТОЧНЫХ ЭНЕРГОЗАТРАТ", "answers": ["метод прямой калориметрии", "метод непрямой калориметрии", "табличный метод", "хронометражно-табличный метод", "велоэргометрия", "алиментарная энергометрия"], "correct_answers": ["метод прямой калориметрии", "метод непрямой калориметрии", "хронометражно-табличный метод", "алиментарная энергометрия"]}
{"quiz": "* ВИДЫ ПИЩЕВОГО СТАТУСА", "answers": ["оптимальный", "обычный", "сбалансированный", "избыточный", "недостаточный"], "correct_answers": ["оптимальный", "обычный", "избыточный", "недостаточный"]}
{"quiz": "* ВАРИАНТЫ НЕДОСТАТОЧНОГО ПИЩЕВОГО СТАТУСА", "answers": ["неполноценный", "преморбидный", "постморбидный", "патологический"], "correct_answers": ["неполноценный", "преморбидный", "патологический"]}
{"quiz": "* ПРИЗНАКИ НЕПОЛНОЦЕННОГО ПИЩЕВОГО СТАТУСА", "answers": ["снижение адаптационных возможностей организма в обычных условиях существования", "снижение функциональных и изменение биохимических показателей", "отсутствие симптомов алиментарной недостаточности", "микросимптомы алиментарной недостаточности"], "correct_answers": ["снижение адаптационных возможностей организма в обычных условиях существования", "отсутствие симптомов алиментарной недостаточности"]}
{"quiz": "* ПРИЗНАКИ ПРЕМОРБИДНОГО ПИЩЕВОГО СТАТУСА", "answers": ["снижение адаптационных возможностей организма в обычных условиях существования", "снижение функциональных и изменение биохимических показателей", "отсутствие симптомов алиментарной недостаточности", "микросимптомы алиментарной недостаточности"], "correct_answers": ["снижение функциональных и изменение биохимических показателей", "микросимптомы алиментарной недостаточности"]}
{"quiz": "* ПРИЗНАКИ ПАТОЛОГИЧЕСКОГО ПИЩЕВОГО СТАТУСА", "answers": ["снижение функциональных и изменение биохимических показателей", "выраженные нарушения структур и функций организма", "микросимптомы алиментарной недостаточности", "выраженные симптомы алиментарной недостаточности"], "correct_answers": ["выраженные нарушения структур и функций организма", "выраженные симптомы алиментарной недостаточности"]}
{"quiz": "* ПОКАЗАТЕЛИ АДЕКВАТНОСТИ ПИТАНИЯ", "answers": ["физиометрические показатели", "антропометрические показатели", "биохимические показатели крови и мочи", "физическое развитие", "состояние здоровье"], "correct_answers": ["антропометрические показатели", "биохимические показатели крови и мочи", "состояние здоровье"]}
{"quiz": "* РОСТО-ВЕСОВЫЕ ИНДЕКСЫ", "answers": ["индекс Кетле", "индекс Брока-Бругша", "индекс Ленца-Бауэра", "индекс Хирша", "индекс Брока"], "correct_answers": ["индекс Кетле", "индекс Брока-Бругша", "индекс Брока"]}
{"quiz": "ЦЕЛЬ ИСПОЛЬЗОВАНИЯ ИНДЕКСА КЕТЛЕ", "answers": ["расчет идеальной массы тела", "расчет фактической массы тела", "оценка пропорций тела", "оценка массы тела"], "correct_answers": ["оценка массы тела"]}
{"quiz": "ФОРМУЛА ДЛЯ РАСЧЕТА ИНДЕКСА КЕТЛЕ", "answers": ["рост (см) / масса (кг)", "рост (м)/масса (кг)", "масса (кг) /квадрат роста (см)", "масса (кг)/квадрат роста (м)"], "correct_answers": ["масса (кг)/квадрат роста (м)"]}
{"quiz": "ЦЕЛЬ ИСПОЛЬЗОВАНИЯ ИНДЕКСА БРОКА-БРУГША", "answers": ["расчет допустимой массы тела", "расчет идеальной массы тела", "оценка пропорций тела", "оценка массы тела"], "correct_answers": ["расчет идеальной массы тела"]}
{"quiz": "* НЕДОСТАТКИ ИНДЕКСА КЕТЛЕ", "answers": ["грубая усредненная оценка", "не учитывает развитие мышечной массы", "не учитывает плотность костей", "ограниченная информативность", "не учитывает пол", "не учитывает возраст"], "correct_answers": ["не учитывает развитие мышечной массы", "не учитывает плотность костей", "ограниченная информативность", "не учитывает пол", "не учитывает возраст"]}
{"quiz": "ФОРМУЛА ДЛЯ РАСЧЕТА ИДЕАЛЬНОЙ МАССЫ ТЕЛА ДЛЯ ЛИЦ С РОСТОМ НИЖЕ 165 СМ, СОГЛАСНО ИНДЕКСУ БРОКА-БРУГША", "answers": ["рост -100", "рост – 105", "рост – 110", "рост – масса тела"], "correct_answers": ["рост -100"]}
{"quiz": "ФОРМУЛА ДЛЯ РАСЧЕТА ИДЕАЛЬНОЙ МАССЫ ТЕЛА ДЛЯ ЛИЦ С РОСТОМ 165 – 175 СМ СОГЛАСНО ИНДЕКСУ БРОКА-БРУГША", "answers": ["рост -100", "рост – 105", "рост – 110", "рост – масса тела"], "correct_answers": ["рост – 105"]}
{"quiz": "ФОРМУЛА ДЛЯ РАСЧЕТА ИДЕАЛЬНОЙ МАССЫ ТЕЛА ДЛЯ ЛИЦ С РОСТОМ ВЫШЕ 175 СМ СОГЛАСНО ИНДЕКСУ БРОКА-БРУГША", "answers": ["рост -100", "рост – 105", "рост – 110", "рост – масса тела"], "correct_answers": ["рост – 110"]}
{"quiz": "* НЕДОСТАТКИ ИНДЕКСА БРОКА", "answers": ["не учитывает возраст", "не учитывает пол", "не учитывает развитие мышечной массы", "не учитывает плотность костей", "грубая усредненная оценка", "ограниченная информативность"], "correct_answers": ["не учитывает возраст", "не учитывает пол", "грубая усредненная оценка", "ограниченная информативность"]}
{"quiz": "ПРИ ВЕЛИЧИНЕ ИНДЕКСА КЕТЛЕ НИЖЕ 18,5 НАБЛЮДАЕТСЯ", "answers": ["недостаток массы тела", "нормальная масса тела", "избыточная масса тела", "ожирение I степени", "ожирение II степени"], "correct_answers": ["недостаток массы тела"]}
{"quiz": "ПРИ ВЕЛИЧИНЕ ИНДЕКСА КЕТЛЕ В ДИАПАЗОНЕ 18,5 – 24,9 НАБЛЮДАЕТСЯ", "answers": ["недостаток массы тела", "нормальная масса тела", "избыточная масса тела", "ожирение I степени", "ожирение II степени"], "correct_answers": ["нормальная масса тела"]}
{"quiz": "ПРИ ВЕЛИЧИНЕ ИНДЕКСА КЕТЛЕ В ДИАПАЗОНЕ 30,0 – 34,9 НАБЛЮДАЕТСЯ", "answers": ["нормальная масса тела", "избыточная масса тела", "ожирение I степени", "ожирение II степени", "ожирение III степени"], "correct_answers": ["ожирение I степени"]}
{"quiz": "ПРИ ВЕЛИЧИНЕ ИНДЕКСА КЕТЛЕ В ДИАПАЗОНЕ 35 – 39,9 НАБЛЮДАЕТСЯ", "answers": ["нормальная масса тела", "избыточная масса тела", "ожирение I степени", "ожирение II степени", "ожирение III степени"], "correct_answers": ["ожирение II степени"]}
{"quiz": "ПРИЧИНА РАЗВИТИЯ АЛИМЕНТАРНОГО МАРАЗМА", "answers": ["недостаточное поступление энергии с пищей", "недостаточное поступление белка с пищей", "недостаточное поступление белка и энергии с пищей", "недостаточное поступление углеводов с пищей", "недостаточное поступление жиров с пищей"], "correct_answers": ["недостаточное поступление белка и энергии с пищей"]}
{"quiz": "ПРИЧИНА РАЗВИТИЯ КВАШИОРКОРА", "answers": ["недостаточное поступление энергии с пищей", "недостаточное поступление белка с пищей", "недостаточное поступление белка и энергии с пищей", "недостаточное поступление углеводов с пищей", "недостаточное поступление жиров с пищей"], "correct_answers": ["недостаточное поступление белка с пищей"]}
{"quiz": "* СИМТОМЫ АЛИМЕНТАРНОГО МАРАЗМА", "answers": ["«змеиная» кожа", "изменение формы и цвета волос", "потеря аппетита", "сохранение ребенком подвижности и хорошего аппетита", "апатия", "лунообразное лицо", "лицо «обезьяны»"], "correct_answers": ["сохранение ребенком подвижности и хорошего аппетита", "лицо «обезьяны»"]}
{"quiz": "* СИМПТОМЫ АЛИМЕНТАРНОГО МАРАЗМА", "answers": ["отек", "отставание роста и массы от возрастных норм", "мышечная дистрофия при отсутствии подкожной клетчатки", "мышечная гипотония с сохранением подкожной клетчатки", "психомоторные нарушения", "слабовыраженные психические нарушения"], "correct_answers": ["отставание роста и массы от возрастных норм", "мышечная дистрофия при отсутствии подкожной клетчатки", "слабовыраженные психические нарушения"]}
{"quiz": "* ПОСТОЯННО ВСТРЕЧАЮЩИЕСЯ СИМТОМЫ КВАШИОРКОРА", "answers": ["отек", "отставание роста и массы от возрастных норм", "мышечная дистрофия при отсутствии подкожной клетчатки", "мышечная гипотония с сохранением подкожной клетчатки", "выраженные психомоторные нарушения", "слабовыраженные психические нарушения"], "correct_answers": ["отек", "отставание роста и массы от возрастных норм", "мышечная гипотония с сохранением подкожной клетчатки", "выраженные психомоторные нарушения"]}
{"quiz": "* ЧАСТО ВСТРЕЧАЮЩИЕСЯ СИМТОМЫ КВАШИОРКОРА", "answers": ["депигментация кожи", "изменение формы и цвета волос", "потеря аппетита", "сохранение ребенком подвижности и хорошего аппетита", "апатия", "лунообразное лицо", "лицо «обезьяны»"], "correct_answers": ["депигментация кожи", "изменение формы и цвета волос", "потеря аппетита", "апатия", "лунообразное лицо"]}
{"quiz": "* ГРУППЫ ПИЩЕВЫХ ОТРАВЛЕНИЙ", "answers": ["микробные", "немикробные", "вирусные", "неясной этиологии"], "correct_answers": ["микробные", "немикробные", "неясной этиологии"]}
{"quiz": "* ГРУППЫ ПИЩЕВЫХ ОТРАВЛЕНИЙ", "answers": ["токсикоинфекции", "токсикозы", "отравления неустановленной этиологии", "отравления смешанной этиологии"], "correct_answers": ["токсикоинфекции", "токсикозы", "отравления смешанной этиологии"]}
{"quiz": "* ХАРАКТЕРНЫЕ ПРИЗНАКИ МИКРОБНЫХ ПИЩЕВЫХ ОТРАВЛЕНИЙ", "answers": ["преимущественно острое течение", "преимущественно хроническое течение", "продолжительный инкубационный период", "короткий инкубационный период", "массовый характер", "немассовый характер", "высокая контагиозность", "отсутствие контагиозности"], "correct_answers": ["преимущественно острое течение", "короткий инкубационный период", "массовый характер", "отсутствие контагиозности"]}
{"quiz": "* МИКРОБНЫЕ ТОКСИКОЗЫ", "answers": ["бактериальные", "вирусные", "микотоксикозы", "сорняковые токсикозы"], "correct_answers": ["бактериальные", "микотоксикозы"]}
{"quiz": "* БАКТЕРИАЛЬНЫЕ ТОКСИКОЗЫ", "answers": ["стрептококковый токсикоз", "стафилококковый токсикоз", "ботулизм", "сорняковый токсикоз"], "correct_answers": ["стафилококковый токсикоз", "ботулизм"]}
{"quiz": "* ПИЩЕВЫЕ МИКОТОКСИКОЗЫ", "answers": ["алиментарно-токсическая алейкия", "алиментарная пароксизмально-токсическая миоглобинурия", "отравление «пьяным хлебом»", "эрготизм", "афлатоксикоз"], "correct_answers": ["алиментарно-токсическая алейкия", "отравление «пьяным хлебом»", "эрготизм", "афлатоксикоз"]}
{"quiz": "ОСНОВНОЙ МЕХАНИЗМ ПЕРЕДАЧИ ПИЩЕВЫХ ТОКСИКОИНФЕКЦИЙ", "answers": ["аэрогенный", "фекально-оральный", "трансмиссивный", "воздушно-капельный"], "correct_answers": ["фекально-оральный"]}
{"quiz": "ОСНОВНОЙ МЕХАНИЗМ ПЕРЕДАЧИ ПИЩЕВЫХ ТОКСИКОИНФЕКЦИЙ", "answers": ["химическое соединение", "токсин", "вирус", "микроскопический грибок"], "correct_answers": ["токсин"]}
{"quiz": "* МИКРООРГАНИЗМЫ, ВЫЗЫВАЮЩИЕ ПИЩЕВЫЕ ТОКСИКОИНФЕКЦИИ", "answers": ["Vibrio cholera", "представители рода Proteus", "Bacillus сereus", "Clostridium tetani", "Сlostridium perfringens"], "correct_answers": ["представители рода Proteus", "Bacillus сereus", "Сlostridium perfringens"]}
{"quiz": "СТЕПЕНЬ ОБСЕМЕНЕНИЯ ПРОДУКТА, ВЫЗЫВАЮЩАЯ РАЗВИТИЕ ПИЩЕВЫХ ТОКСИКОИНФЕКЦИЙ", "answers": ["10^5 -10^6 микробных тел в 1 грамме или 1 мл продукта", "10^3 -10^4 микробных тел в 1 грамме или 1 мл продукта", "100-500 микробных тел в 1 грамме или 1 мл продукта", "несколько десятков микробных тел в 1 грамме или 1 мл продукта"], "correct_answers": ["10^5 -10^6 микробных тел в 1 грамме или 1 мл продукта"]}
{"quiz": "МИКРООРГАНИЗМ, ИЗМЕНЯЮЩИЙ ОРГАНОЛЕПТИЧЕСКИЕ СВОЙСТВА ПРОДУКТА (ОСЛИЗНЕНИЕ И ГОРЬКИЙ ВКУС)", "answers": ["Proteus", "Escherichia coli", "Clostridium perfringens", "Enterococcus"], "correct_answers": ["Enterococcus"]}
{"quiz": "* ИСТОЧНИК ЗАРАЖЕНИЯ, ХАРАКТЕРНЫЙ ДЛЯ СТАФИЛОКОККОВОГО ТОКСИКОЗА", "answers": ["гнойно-воспалительные заболевания кожи у персонала", "синантропные мухи", "гнойно-воспалительные заболевания животных", "инфекционно-воспалительные заболевания ВДП у персонала"], "correct_answers": ["гнойно-воспалительные заболевания кожи у персонала", "гнойно-воспалительные заболевания животных", "инфекционно-воспалительные заболевания ВДП у персонала"]}
{"quiz": "* ПРОДУКТЫ ПИТАНИЯ, С КОТОРЫМИ НАБОЛЕЕ ЧАСТО СВЯЗАНЫ СЛУЧАИ ВОЗНИКНОВЕНИЯ СТАФИЛОКОККОВОГО ТОКСИКОЗА", "answers": ["яйца", "изделия из фарша", "торты и пирожные с заварным кремом", "молоко и молочные продукты", "рыбные и мясные консервы"], "correct_answers": ["изделия из фарша", "торты и пирожные с заварным кремом", "молоко и молочные продукты"]}
{"quiz": "* ФАКТОРЫ, ИНГИБИРУЮЩИЕ РОСТ И РАЗМНОЖЕНИЕ СТАФИЛОКОККОВ", "answers": ["рH ниже 4,5", "рH выше 9,0", "содержание сахара ниже 60%", "содержание сахара более 60%", "температура выше 45ºC", "температура ниже 4ºC"], "correct_answers": ["рH ниже 4,5", "содержание сахара более 60%", "температура выше 45ºC", "температура ниже 4ºC"]}
{"quiz": "ПИЩЕВОЕ ОТРАВЛЕНИЕ, ХАРАКТЕРИЗУЮЩЕЕСЯ ПОЯВЛЕНИЕМ СИМПТОМОВ ДИПЛОПИИ, ДИСФАГИИ, ДИЗАРТРИИ, ДИСФОНИИ", "answers": ["афлатоксикоз", "ботулизм", "эрготизм", "отравление «пьяным хлебом»"], "correct_answers": ["ботулизм"]}
{"quiz": "* СПЕЦИФИЧЕСКИЕ СИМПТОМЫ БОТУЛИЗМА", "answers": ["диплопия", "афония", "аносмия", "афагия", "анурия"], "correct_answers": ["диплопия", "афония", "афагия"]}
{"quiz": "* ПРОДУКТЫ ПИТАНИЯ, С КОТОРЫМИ НАБОЛЕЕ ЧАСТО СВЯЗАНЫ СЛУЧАИ ВОЗНИКНОВЕНИЯ БОТУЛИЗМА", "answers": ["молоко и молочные продукты домашнего изготовления", "грибы домашнего консервирования", "овощные консервы домашнего консервирования", "рыба домашнего копчения"], "correct_answers": ["грибы домашнего консервирования", "овощные консервы домашнего консервирования", "рыба домашнего копчения"]}
{"quiz": "ПРАВИЛА МЫТЬЯ ЗЕЛЕНИ ДЛЯ УДАЛЕНИЯ ПОЧВЫ", "answers": ["длительное промывание под холодной проточной водой", "длительное промывание под горячей проточной водой", "многократное погружение в емкость с большим количеством воды", "замачивание в холодной воде с добавлением соли"], "correct_answers": ["многократное погружение в емкость с большим количеством воды"]}
{"quiz": "* ФАКТОРЫ, СПОСОБСТВУЮЩИЕ ПРОРАСТАНИЮ СПОР В ВЕГЕТАТИВНЫЕ ФОРМЫ С ПОСЛЕДУЮЩЕЙ ПРОДУКЦИЕЙ БОТУЛОТОКСИНА", "answers": ["доступ кислорода", "анаэробные условия", "длительный период времени", "короткий период времени", "холод", "тепло"], "correct_answers": ["анаэробные условия", "длительный период времени", "тепло"]}
{"quiz": "* ПИЩЕВЫЕ МИКОТОКСИКОЗЫ ВЫЗЫВАЮТ ТОКСИНЫ ГРИБОВ РОДА", "answers": ["Amanita", "Aspergillus", "Fusarium", "Claviceps purpurea", "Candida"], "correct_answers": ["Aspergillus", "Fusarium", "Claviceps purpurea"]}
{"quiz": "АЛИМЕНТАРНО - ТОКСИЧЕСКАЯ АЛЕЙКИЯ ОБУСЛОВЛЕНА УПОТРЕБЛЕНИЕМ В ПИЩУ ПРОДУКТОВ ИЗ ЗЕРНА, СОДЕРЖАЩЕГО ТОКСИНЫ ГРИБОВ", "answers": ["Aspergillus flavus", "Claviceps purpurea", "Fusarium graminearum", "Fusarium sporotrichioides"], "correct_answers": ["Fusarium sporotrichioides"]}
{"quiz": "ОТРАВЛЕНИЕ «ПЬЯНЫМ ХЛЕБОМ» ОБУСЛОВЛЕНО УПОТРЕБЛЕНИЕМ В ПИЩУ ПРОДУКТОВ ИЗ ЗЕРНА, СОДЕРЖАЩЕГО ТОКСИНЫ ГРИБОВ", "answers": ["Aspergillus flavus", "Claviceps purpurea", "Fusarium graminearum", "Fusarium sporotrichioides"], "correct_answers": ["Fusarium graminearum"]}
{"quiz": "* СИМПТОМЫ АЛИМЕНТАРНО-ТОКСИЧЕСКОЙ АЛЕЙКИИ", "answers": ["некротическая ангина", "диплопия", "носовые кровотечения", "дисфагия", "точечные кровоизлияния на коже"], "correct_answers": ["некротическая ангина", "носовые кровотечения", "точечные кровоизлияния на коже"]}
{"quiz": "* СИМПТОМЫ АЛИМЕНТАРНО-ТОКСИЧЕСКОЙ АЛЕЙКИИ", "answers": ["экзофтальм", "маточные кровотечения", "аменорея", "стоматит", "тахикардия"], "correct_answers": ["маточные кровотечения", "стоматит", "тахикардия"]}
{"quiz": "* ФОРМЫ ТЕЧЕНИЯ ЭРГОТИЗМА", "answers": ["конвульсивная", "гангренозная", "смешанная", "атипическая"], "correct_answers": ["конвульсивная", "гангренозная", "смешанная"]}
{"quiz": "* ФАКТОРЫ, СПОСОБСТВУЮЩИЕ НАКОПЛЕНИЮ СТАФИЛОКОККОВОГО ТОКСИНА В ПРОДУКТАХ ПИТАНИЯ", "answers": ["температура 30-37ºC", "температура 18-22ºC", "добавление черного хлеба к мясному фаршу", "добавление белого хлеба к мясному фаршу"], "correct_answers": ["температура 30-37ºC", "добавление белого хлеба к мясному фаршу"]}
{"quiz": "* ФАКТОРЫ, СПОСОБСТВУЮЩИЕ НАКОПЛЕНИЮ СТАФИЛОКОККОВОГО ТОКСИНА В ПРОДУКТАХ ПИТАНИЯ", "answers": ["афлатоксикоз", "ботулизм", "эрготизм", "отравление «пьяным хлебом»"], "correct_answers": ["ботулизм"]}
{"quiz": "ВЕДУЩИЙ ЭТИОЛОГИЧЕСКИЙ ФАКТОР В РАЗВИТИИ ПИЩЕВЫХ ТОКСИКОЗОВ", "answers": ["бактерия", "токсин", "вирус", "микроскопический гриб"], "correct_answers": ["токсин"]}
{"quiz": "ПРИ ВЕЛИЧИНЕ ИНДЕКСА КЕТЛЕ 35 И ВЫШЕ НАБЛЮДАЕТСЯ", "answers": ["избыточная масса тела", "ожирение I степени", "ожирение II степени", "ожирение III степени", "ожирение IV степени"], "correct_answers": ["ожирение III степени"]}{"quiz": "ПРИ ВЕЛИЧИНЕ ИНДЕКСА КЕТЛЕ В ДИАПАЗОНЕ 25,0 – 29,9 НАБЛЮДАЕТСЯ", "answers": ["нормальная масса тела", "избыточная масса тела", "ожирение I степени", "ожирение II степени", "ожирение III степени"], "correct_answers": ["избыточная масса тела"]}
{"quiz": "РЕКОМЕНДУЕМАЯ ДОЛЯ БЕЛКОВ ЖИВОТНОГО ПРОИСХОЖДЕНИЯ ДЛЯ ВЗРОСЛОГО НАСЕЛЕНИЯ СОСТАВЛЯЕТ (% ОТ ОБЩЕГО БЕЛКА) СОГЛАСНО МЕТОДИЧЕСКИМ РЕКОМЕНДАЦИЯМ (МР 2.3.1.0253—21)", "answers": ["30%", "40%", "50%", "60%"], "correct_answers": ["50%"]}{"quiz": "* ОПТИМАЛЬНОЕ РАСПРЕДЕЛЕНИЕ СУТОЧНОЙ КАЛОРИЙНОСТИ МЕЖДУ ОТДЕЛЬНЫМИ ПРИЕМАМИ ПИЩИ ПРИ 4-Х КРАТНОМ ПИТАНИИ", "answers": ["I завтрак - 25%", "I завтрак - 30 %", "II завтрак/полдник – 5%", "II завтрак/полдник – 15%", "обед - 45%", "обед - 35%", "ужин - 20%", "ужин - 25%"], "correct_answers": ["I завтрак - 25%", "II завтрак/полдник – 15%", "обед - 35%", "ужин - 25%"]}{"quiz": "НА НИЖНЕМ ЯРУСЕ ПИРАМИДЫ ЗДОРОВОГО ПИТАНИЯ РАСПОЛОЖЕНЫ", "answers": ["мясные продукты", "молочные продукты", "злаковые продукты", "овощи и фрукты"], "correct_answers": ["злаковые продукты"]}{"quiz": "* ВИДЫ ПИТАНИЯ ЗДОРОВОГО ЧЕЛОВЕКА", "answers": ["рациональное", "профилактическое", "диетическое", "здоровое", "лечебное"], "correct_answers": ["рациональное", "профилактическое", "здоровое"]}{"quiz": "РАЗГРУЗОЧНЫЕ ПЛОЩАДКИ ОТНОСЯТСЯ К ГРУППЕ:", "answers": ["технических помещений", "складских помещений", "производственных помещений", "служебных и бытовых помещений"], "correct_answers": ["складских помещений"]}